[
  { "id": 1, "username": "user1", "password": "pass1" },
  { "id": 2, "username": "user2", "password": "pass2" },
  { "id": 3, "username": "user3", "password": "pass3" },
  { "id": 4, "username": "user4", "password": "pass4" },
  { "id": 5, "username": "user5", "password": "pass5" },
  { "id": 6, "username": "user6", "password": "pass6" },
  { "id": 7, "username": "user7", "password": "pass7" },
  { "id": 8, "username": "user8", "password": "pass8" },
  { "id": 9, "username": "user9", "password": "pass9" },
  { "id": 10, "username": "user10", "password": "pass10" },
  { "id": 11, "username": "user11", "password": "pass11" },
  { "id": 12, "username": "user12", "password": "pass12" },
  { "id": 13, "username": "user13", "password": "pass13" },
  { "id": 14, "username": "user14", "password": "pass14" },
  { "id": 15, "username": "user15", "password": "pass15" },
  { "id": 16, "username": "user16", "password": "pass16" },
  { "id": 17, "username": "user17", "password": "pass17" },
  { "id": 18, "username": "user18", "password": "pass18" },
  { "id": 19, "username": "user19", "password": "pass19" },
  { "id": 20, "username": "user20", "password": "pass20" },
  { "id": 21, "username": "user21", "password": "pass21" },
  { "id": 22, "username": "user22", "password": "pass22" },
  { "id": 23, "username": "user23", "password": "pass23" },
  { "id": 24, "username": "user24", "password": "pass24" },
  { "id": 25, "username": "user25", "password": "pass25" },
  { "id": 26, "username": "user26", "password": "pass26" },
  { "id": 27, "username": "user27", "password": "pass27" },
  { "id": 28, "username": "user28", "password": "pass28" },
  { "id": 29, "username": "user29", "password": "pass29" },
  { "id": 30, "username": "user30", "password": "pass30" },
  { "id": 31, "username": "user31", "password": "pass31" },
  { "id": 32, "username": "user32", "password": "pass32" },
  { "id": 33, "username": "user33", "password": "pass33" },
  { "id": 34, "username": "user34", "password": "pass34" },
  { "id": 35, "username": "user35", "password": "pass35" },
  { "id": 36, "username": "user36", "password": "pass36" },
  { "id": 37, "username": "user37", "password": "pass37" },
  { "id": 38, "username": "user38", "password": "pass38" },
  { "id": 39, "username": "user39", "password": "pass39" },
  { "id": 40, "username": "user40", "password": "pass40" },
  { "id": 41, "username": "user41", "password": "pass41" },
  { "id": 42, "username": "user42", "password": "pass42" },
  { "id": 43, "username": "user43", "password": "pass43" },
  { "id": 44, "username": "user44", "password": "pass44" },
  { "id": 45, "username": "user45", "password": "pass45" },
  { "id": 46, "username": "user46", "password": "pass46" },
  { "id": 47, "username": "user47", "password": "pass47" },
  { "id": 48, "username": "user48", "password": "pass48" },
  { "id": 49, "username": "user49", "password": "pass49" },
  { "id": 50, "username": "user50", "password": "pass50" },
  { "id": 51, "username": "user51", "password": "pass51" },
  { "id": 52, "username": "user52", "password": "pass52" },
  { "id": 53, "username": "user53", "password": "pass53" },
  { "id": 54, "username": "user54", "password": "pass54" },
  { "id": 55, "username": "user55", "password": "pass55" },
  { "id": 56, "username": "user56", "password": "pass56" },
  { "id": 57, "username": "user57", "password": "pass57" },
  { "id": 58, "username": "user58", "password": "pass58" },
  { "id": 59, "username": "user59", "password": "pass59" },
  { "id": 60, "username": "user60", "password": "pass60" },
  { "id": 61, "username": "user61", "password": "pass61" },
  { "id": 62, "username": "user62", "password": "pass62" },
  { "id": 63, "username": "user63", "password": "pass63" },
  { "id": 64, "username": "user64", "password": "pass64" },
  { "id": 65, "username": "user65", "password": "pass65" },
  { "id": 66, "username": "user66", "password": "pass66" },
  { "id": 67, "username": "user67", "password": "pass67" },
  { "id": 68, "username": "user68", "password": "pass68" },
  { "id": 69, "username": "user69", "password": "pass69" },
  { "id": 70, "username": "user70", "password": "pass70" },
  { "id": 71, "username": "user71", "password": "pass71" },
  { "id": 72, "username": "user72", "password": "pass72" },
  { "id": 73, "username": "user73", "password": "pass73" },
  { "id": 74, "username": "user74", "password": "pass74" },
  { "id": 75, "username": "user75", "password": "pass75" },
  { "id": 76, "username": "user76", "password": "pass76" },
  { "id": 77, "username": "user77", "password": "pass77" },
  { "id": 78, "username": "user78", "password": "pass78" },
  { "id": 79, "username": "user79", "password": "pass79" },
  { "id": 80, "username": "user80", "password": "pass80" },
  { "id": 81, "username": "user81", "password": "pass81" },
  { "id": 82, "username": "user82", "password": "pass82" },
  { "id": 83, "username": "user83", "password": "pass83" },
  { "id": 84, "username": "user84", "password": "pass84" },
  { "id": 85, "username": "user85", "password": "pass85" },
  { "id": 86, "username": "user86", "password": "pass86" },
  { "id": 87, "username": "user87", "password": "pass87" },
  { "id": 88, "username": "user88", "password": "pass88" },
  { "id": 89, "username": "user89", "password": "pass89" },
  { "id": 90, "username": "user90", "password": "pass90" },
  { "id": 91, "username": "user91", "password": "pass91" },
  { "id": 92, "username": "user92", "password": "pass92" },
  { "id": 93, "username": "user93", "password": "pass93" },
  { "id": 94, "username": "user94", "password": "pass94" },
  { "id": 95, "username": "user95", "password": "pass95" },
  { "id": 96, "username": "user96", "password": "pass96" },
  { "id": 97, "username": "user97", "password": "pass97" },
  { "id": 98, "username": "user98", "password": "pass98" },
  { "id": 99, "username": "user99", "password": "pass99" },
  { "id": 100, "username": "user100", "password": "pass100" }
]